listmonk/__init__.py
listmonk/api/__init__.py
listmonk/api/admin_api.py
listmonk/api/bounces_api.py
listmonk/api/campaigns_api.py
listmonk/api/import_api.py
listmonk/api/lists_api.py
listmonk/api/logs_api.py
listmonk/api/maintenance_api.py
listmonk/api/media_api.py
listmonk/api/miscellaneous_api.py
listmonk/api/public_api.py
listmonk/api/settings_api.py
listmonk/api/subscribers_api.py
listmonk/api/templates_api.py
listmonk/api/transactional_api.py
listmonk/api_client.py
listmonk/api_response.py
listmonk/configuration.py
listmonk/exceptions.py
listmonk/models/__init__.py
listmonk/models/bounce.py
listmonk/models/bounce_results_inner.py
listmonk/models/bounce_results_inner_campaign.py
listmonk/models/campaign.py
listmonk/models/campaign_analytics_count.py
listmonk/models/campaign_content_request.py
listmonk/models/campaign_request.py
listmonk/models/campaign_request_send_at.py
listmonk/models/campaign_stats.py
listmonk/models/campaign_update.py
listmonk/models/create_campaign200_response.py
listmonk/models/create_list200_response.py
listmonk/models/create_subscriber200_response.py
listmonk/models/dashboard_chart.py
listmonk/models/dashboard_chart_link_clicks_inner.py
listmonk/models/dashboard_count.py
listmonk/models/dashboard_count_data.py
listmonk/models/dashboard_count_data_campaigns.py
listmonk/models/dashboard_count_data_campaigns_by_status.py
listmonk/models/dashboard_count_data_lists.py
listmonk/models/dashboard_count_data_subscribers.py
listmonk/models/delete_gc_subscribers200_response.py
listmonk/models/delete_gc_subscribers200_response_data.py
listmonk/models/get_bounce_by_id200_response.py
listmonk/models/get_bounces200_response.py
listmonk/models/get_bounces200_response_data.py
listmonk/models/get_campaign_analytics200_response.py
listmonk/models/get_campaign_by_id200_response.py
listmonk/models/get_campaigns200_response.py
listmonk/models/get_campaigns200_response_data.py
listmonk/models/get_dashboard_charts200_response.py
python_listmonk-0.0.0.dist-info/METADATA
python_listmonk-0.0.0.dist-info/WHEEL
python_listmonk-0.0.0.dist-info/RECORD
